{
  "promptId": "P13",
  "condition": "aether",
  "iteration": 3,
  "passed": true,
  "tokensIn": 1037,
  "tokensOut": 493,
  "tokensTotal": 1530,
  "latencyMs": 13055,
  "wallMs": 13055,
  "files": [
    {
      "path": "unnamed.ts",
      "length": 997
    },
    {
      "path": "unnamed.ts",
      "length": 506
    }
  ],
  "rules": [
    {
      "id": "g1",
      "passed": true,
      "skipped": false
    },
    {
      "id": "g2",
      "passed": true,
      "skipped": false
    },
    {
      "id": "g3",
      "passed": true,
      "skipped": false
    },
    {
      "id": "g4",
      "passed": true,
      "skipped": true,
      "message": "Deferred: test runner integration is Session 2"
    },
    {
      "id": "g5",
      "passed": true,
      "skipped": false
    }
  ]
}